nigsp/__init__.py
nigsp/_version.py
nigsp/blocks.py
nigsp/conftest.py
nigsp/due.py
nigsp/io.py
nigsp/objects.py
nigsp/references.py
nigsp/utils.py
nigsp/viz.py
nigsp/workflow.py
nigsp/cli/__init__.py
nigsp/cli/run.py
nigsp/operations/__init__.py
nigsp/operations/graph.py
nigsp/operations/laplacian.py
nigsp/operations/metrics.py
nigsp/operations/nifti.py
nigsp/operations/surrogates.py
nigsp/operations/timeseries.py
nigsp/tests/__init__.py
nigsp/tests/test_blocks.py
nigsp/tests/test_graph.py
nigsp/tests/test_integration.py
nigsp/tests/test_io.py
nigsp/tests/test_laplacian.py
nigsp/tests/test_metrics.py
nigsp/tests/test_nifti.py
nigsp/tests/test_objects.py
nigsp/tests/test_surrogates.py
nigsp/tests/test_timeseries.py
nigsp/tests/test_utils.py
nigsp/tests/test_viz.py
nigsp-0.19.0.dist-info/LICENSE
nigsp-0.19.0.dist-info/METADATA
nigsp-0.19.0.dist-info/WHEEL
nigsp-0.19.0.dist-info/entry_points.txt
nigsp-0.19.0.dist-info/top_level.txt
nigsp-0.19.0.dist-info/RECORD
