Metadata-Version: 2.1
Name: nigsp
Version: 0.19.0
Summary: A python library (and toolbox!) to run Graph Signal Processing on multimodal MRI data.
Home-page: https://github.com/MIPLabCH/nigsp
Download-URL: https://github.com/MIPLabCH/nigsp
Author: Stefano Moia
Maintainer: Stefano Moia
Maintainer-email: s.moia.research@gmail.com
License: Apache-2.0
Platform: OS Independent
Classifier: Development Status :: 4 - Beta
Classifier: Intended Audience :: Science/Research
Classifier: License :: OSI Approved :: Apache Software License
Classifier: Programming Language :: Python :: 3.6
Classifier: Programming Language :: Python :: 3.7
Classifier: Programming Language :: Python :: 3.8
Classifier: Programming Language :: Python :: 3.9
Classifier: Programming Language :: Python :: 3.10
Provides: nigsp
Requires-Python: >=3.6
License-File: LICENSE
Requires-Dist: numpy >=1.17
Requires-Dist: duecredit
Provides-Extra: all
Requires-Dist: nibabel ; extra == 'all'
Requires-Dist: pymatreader ; extra == 'all'
Requires-Dist: scipy ; extra == 'all'
Requires-Dist: matplotlib >=3.1.1 ; extra == 'all'
Requires-Dist: nilearn >=0.7.0 ; extra == 'all'
Provides-Extra: dev
Requires-Dist: pre-commit ; extra == 'dev'
Requires-Dist: furo ; extra == 'dev'
Requires-Dist: memory-profiler ; extra == 'dev'
Requires-Dist: myst-parser ; extra == 'dev'
Requires-Dist: numpydoc ; extra == 'dev'
Requires-Dist: sphinx >=2.0 ; extra == 'dev'
Requires-Dist: sphinx-argparse ; extra == 'dev'
Requires-Dist: sphinxcontrib-apidoc ; extra == 'dev'
Requires-Dist: sphinxcontrib-bibtex ; extra == 'dev'
Requires-Dist: sphinx-copybutton ; extra == 'dev'
Requires-Dist: sphinx-design ; extra == 'dev'
Requires-Dist: sphinx-gallery ; extra == 'dev'
Requires-Dist: sphinx-issues ; extra == 'dev'
Requires-Dist: nibabel ; extra == 'dev'
Requires-Dist: pymatreader ; extra == 'dev'
Requires-Dist: scipy ; extra == 'dev'
Requires-Dist: matplotlib >=3.1.1 ; extra == 'dev'
Requires-Dist: nilearn >=0.7.0 ; extra == 'dev'
Requires-Dist: flake8 >=4.0 ; extra == 'dev'
Requires-Dist: black <23.0.0 ; extra == 'dev'
Requires-Dist: isort <6.0.0 ; extra == 'dev'
Requires-Dist: pydocstyle ; extra == 'dev'
Requires-Dist: codespell ; extra == 'dev'
Requires-Dist: pytest >=8.0 ; extra == 'dev'
Requires-Dist: pytest-cov ; extra == 'dev'
Requires-Dist: coverage ; extra == 'dev'
Provides-Extra: devtools
Requires-Dist: pre-commit ; extra == 'devtools'
Provides-Extra: doc
Requires-Dist: furo ; extra == 'doc'
Requires-Dist: memory-profiler ; extra == 'doc'
Requires-Dist: myst-parser ; extra == 'doc'
Requires-Dist: numpydoc ; extra == 'doc'
Requires-Dist: sphinx >=2.0 ; extra == 'doc'
Requires-Dist: sphinx-argparse ; extra == 'doc'
Requires-Dist: sphinxcontrib-apidoc ; extra == 'doc'
Requires-Dist: sphinxcontrib-bibtex ; extra == 'doc'
Requires-Dist: sphinx-copybutton ; extra == 'doc'
Requires-Dist: sphinx-design ; extra == 'doc'
Requires-Dist: sphinx-gallery ; extra == 'doc'
Requires-Dist: sphinx-issues ; extra == 'doc'
Provides-Extra: mat
Requires-Dist: pymatreader ; extra == 'mat'
Requires-Dist: scipy ; extra == 'mat'
Provides-Extra: nifti
Requires-Dist: nibabel ; extra == 'nifti'
Provides-Extra: style
Requires-Dist: flake8 >=4.0 ; extra == 'style'
Requires-Dist: black <23.0.0 ; extra == 'style'
Requires-Dist: isort <6.0.0 ; extra == 'style'
Requires-Dist: pydocstyle ; extra == 'style'
Requires-Dist: codespell ; extra == 'style'
Provides-Extra: test
Requires-Dist: nibabel ; extra == 'test'
Requires-Dist: pymatreader ; extra == 'test'
Requires-Dist: scipy ; extra == 'test'
Requires-Dist: matplotlib >=3.1.1 ; extra == 'test'
Requires-Dist: nilearn >=0.7.0 ; extra == 'test'
Requires-Dist: flake8 >=4.0 ; extra == 'test'
Requires-Dist: black <23.0.0 ; extra == 'test'
Requires-Dist: isort <6.0.0 ; extra == 'test'
Requires-Dist: pydocstyle ; extra == 'test'
Requires-Dist: codespell ; extra == 'test'
Requires-Dist: pytest >=8.0 ; extra == 'test'
Requires-Dist: pytest-cov ; extra == 'test'
Requires-Dist: coverage ; extra == 'test'
Provides-Extra: viz
Requires-Dist: matplotlib >=3.1.1 ; extra == 'viz'
Requires-Dist: nilearn >=0.7.0 ; extra == 'viz'
